libpypostal/data_utils.py
libpypostal/libpostal_download_data
libpypostal/__init__.py
libpypostal/_parser.cpython-310-i386-linux-gnu.so
libpypostal/parser.py
libpypostal/version.py
libpypostal-0.0.6.dist-info/WHEEL
libpypostal-0.0.6.dist-info/LICENSE
libpypostal-0.0.6.dist-info/top_level.txt
libpypostal-0.0.6.dist-info/RECORD
libpypostal-0.0.6.dist-info/METADATA
libpypostal.libs/libpostal-3e15d225.so.1.0.1
