Metadata-Version: 2.1
Name: libpypostal
Version: 0.0.6
Summary: Python bindings for libpostal C library.
License: MIT License
Project-URL: Repository, https://github.com/gmweaver/libpypostal
Classifier: Development Status :: 3 - Alpha
Classifier: Programming Language :: Python :: 3
Classifier: Programming Language :: Python :: 3.8
Classifier: Programming Language :: Python :: 3.9
Classifier: Programming Language :: Python :: 3.10
Classifier: Programming Language :: Python :: 3.11
Classifier: Programming Language :: Python :: 3.12
Requires-Python: >=3.8
License-File: LICENSE
